bipbop_microservices/__init__.py
bipbop_microservices/microservices.py
bipbop_microservices-0.0.8.dist-info/LICENSE
bipbop_microservices-0.0.8.dist-info/METADATA
bipbop_microservices-0.0.8.dist-info/WHEEL
bipbop_microservices-0.0.8.dist-info/top_level.txt
bipbop_microservices-0.0.8.dist-info/RECORD
