Metadata-Version: 2.1
Name: bipbop-microservices
Version: 0.0.8
Summary: IPC between BIPBOP APPs
Home-page: https://github.com/bipbop/bipbop-microservices
Author: Lucas Fernando Amorim
Author-email: lf.amorim@bipbop.com.br
License: UNKNOWN
Platform: UNKNOWN
Classifier: Development Status :: 5 - Production/Stable
Classifier: Intended Audience :: Customer Service
Classifier: License :: OSI Approved :: MIT License
Requires-Python: >=3.6
